wrtview/__init__.py
wrtview/vendors
wrtview/wrtview.py
wrtview-0.9.1.dist-info/LICENSE
wrtview-0.9.1.dist-info/METADATA
wrtview-0.9.1.dist-info/WHEEL
wrtview-0.9.1.dist-info/entry_points.txt
wrtview-0.9.1.dist-info/top_level.txt
wrtview-0.9.1.dist-info/RECORD
