Metadata-Version: 2.1
Name: wrtview
Version: 0.9.1
Summary: Network information viewer for OpenWRT
Home-page: https://github.com/ropg/wrtview
Author: Rop Gonggrijp
License: MIT
Project-URL: Documentation, https://github.com/ropg/wrtview/blob/master/README.md
Project-URL: Source, https://github.com/ropg/wrtview
Project-URL: Tracker, https://github.com/ropg/wrtview/issues
Keywords: openwrt,networking
Platform: UNKNOWN
Classifier: Development Status :: 3 - Alpha
Classifier: Programming Language :: Python :: 3
Requires-Python: >=3.5
